{
  "users": [
    {
      "id": 1,
      "name": "Myra"
    },
    {
      "name": "Elsie Price",
      "id": 3
    },
    {
      "name": "Harold Strosin",
      "id": 4
    },
    {
      "id": "0c49",
      "name": "Christian Volkman"
    },
    {
      "id": "ea9b",
      "name": "Sheri Howell II"
    }
  ],
  "albums": [
    {
      "id": 10,
      "title": "Hiking Trip",
      "userId": 1
    },
    {
      "id": "fb38",
      "userId": 1,
      "title": "Oriental Granite Gloves"
    },
    {
      "id": "23f5",
      "userId": 1,
      "title": "Rustic Rubber Fish"
    },
    {
      "id": "9332",
      "userId": 1,
      "title": "Handmade Cotton Bike"
    },
    {
      "id": "b141",
      "userId": 1,
      "title": "Practical Granite Soap"
    },
    {
      "id": "5832",
      "userId": 1,
      "title": "Sleek Metal Bacon"
    },
    {
      "id": "6709",
      "userId": 1,
      "title": "Intelligent Fresh Ball"
    },
    {
      "id": "99ec",
      "userId": 1,
      "title": "Licensed Steel Ball"
    },
    {
      "id": "24d7",
      "userId": 1,
      "title": "Generic Granite Chair"
    },
    {
      "id": "0ab7",
      "userId": 1,
      "title": "Tasty Granite Cheese"
    },
    {
      "id": "3744",
      "userId": 1,
      "title": "Rustic Rubber Ball"
    },
    {
      "id": "785c",
      "userId": 1,
      "title": "Generic Wooden Chair"
    },
    {
      "id": "6d31",
      "userId": 1,
      "title": "Electronic Frozen Gloves"
    },
    {
      "id": "d01d",
      "userId": 1,
      "title": "Unbranded Soft Shoes"
    },
    {
      "id": "68ef",
      "userId": 1,
      "title": "Licensed Wooden Towels"
    },
    {
      "id": "3ced",
      "userId": 3,
      "title": "Generic Concrete Computer"
    },
    {
      "id": "9de4",
      "userId": 1,
      "title": "Handmade Frozen Chair"
    },
    {
      "id": "4d08",
      "userId": 1,
      "title": "Awesome Steel Chicken"
    },
    {
      "id": "f736",
      "userId": 1,
      "title": "Practical Metal Ball"
    },
    {
      "id": "2548",
      "userId": 1,
      "title": "Sleek Steel Keyboard"
    },
    {
      "id": "115e",
      "userId": 1,
      "title": "Licensed Rubber Chips"
    }
  ],
  "photos": []
}